pluralsingular/__init__.py
pluralsingular/lang/de.py
pluralsingular/lang/el.py
pluralsingular/lang/en.py
pluralsingular/lang/es.py
pluralsingular/lang/fr.py
pluralsingular/lang/gl.py
pluralsingular/lang/it.py
pluralsingular/lang/nl.py
pluralsingular/lang/pt.py
pluralsingular/lang/ru.py
pluralsingular/lang/uk.py
pluralsingular-0.1.2.dist-info/LICENSE
pluralsingular-0.1.2.dist-info/WHEEL
pluralsingular-0.1.2.dist-info/METADATA
pluralsingular-0.1.2.dist-info/RECORD
