Metadata-Version: 2.1
Name: pluralsingular
Version: 0.1.2
Summary: This module provides functionality to pluralize and singularize words
Author-email: Salvador Fandiño <sfandino@yahoo.com>
Classifier: License :: OSI Approved :: MIT License
Classifier: Programming Language :: Python :: 3
Classifier: Programming Language :: Python :: 3.6
Classifier: Programming Language :: Python :: 3.7
Classifier: Programming Language :: Python :: 3.8
Classifier: Programming Language :: Python :: 3.9
Classifier: Programming Language :: Python :: 3.10
Classifier: Programming Language :: Python :: 3.11
Project-URL: Home, http://github.com/salva/py-pluralsingular
